ignition_automation_tools/__init__.py
ignition_automation_tools/Components/BasicComponent.py
ignition_automation_tools/Components/__init__.py
ignition_automation_tools/Components/Common/Button.py
ignition_automation_tools/Components/Common/FileUpload.py
ignition_automation_tools/Components/Common/TextInput.py
ignition_automation_tools/Components/Common/__init__.py
ignition_automation_tools/Components/PerspectiveComponents/Tooltip.py
ignition_automation_tools/Components/PerspectiveComponents/__init__.py
ignition_automation_tools/Components/PerspectiveComponents/Charts/Pie.py
ignition_automation_tools/Components/PerspectiveComponents/Charts/PowerChart.py
ignition_automation_tools/Components/PerspectiveComponents/Charts/TimeSeriesChart.py
ignition_automation_tools/Components/PerspectiveComponents/Charts/XYChart.py
ignition_automation_tools/Components/PerspectiveComponents/Charts/__init__.py
ignition_automation_tools/Components/PerspectiveComponents/Common/Checkbox.py
ignition_automation_tools/Components/PerspectiveComponents/Common/ComponentModal.py
ignition_automation_tools/Components/PerspectiveComponents/Common/DateRangeSelector.py
ignition_automation_tools/Components/PerspectiveComponents/Common/DateTimePicker.py
ignition_automation_tools/Components/PerspectiveComponents/Common/Dropdown.py
ignition_automation_tools/Components/PerspectiveComponents/Common/Icon.py
ignition_automation_tools/Components/PerspectiveComponents/Common/Table.py
ignition_automation_tools/Components/PerspectiveComponents/Common/TagBrowseTree.py
ignition_automation_tools/Components/PerspectiveComponents/Common/Tree.py
ignition_automation_tools/Components/PerspectiveComponents/Common/__init__.py
ignition_automation_tools/Components/PerspectiveComponents/Common/TablePieces/Body.py
ignition_automation_tools/Components/PerspectiveComponents/Common/TablePieces/Filter.py
ignition_automation_tools/Components/PerspectiveComponents/Common/TablePieces/HeaderAndFooter.py
dg_ignition_selenium-0.1.3.dist-info/METADATA
dg_ignition_selenium-0.1.3.dist-info/WHEEL
dg_ignition_selenium-0.1.3.dist-info/top_level.txt
dg_ignition_selenium-0.1.3.dist-info/RECORD
