Metadata-Version: 2.4
Name: dg-ignition-selenium
Version: 0.1.3
Summary: Automation library for Ignition Perspective based on Inductive Automation's ignition-automation-tools.
Author-email: Design Group <keith.gamble@bwdesigngroup.com>
License-Expression: MIT
Project-URL: Homepage, https://github.com/design-group/dg-ignition-selenium
Project-URL: Bug Tracker, https://github.com/design-group/dg-ignition-selenium/issues
Requires-Python: >=3.8
Requires-Dist: selenium>=4.0.0
Dynamic: requires-python
